RetrievalMind/__init__.py
RetrievalMind/data_ingestion/__init__.py
RetrievalMind/data_ingestion/pdf_ingestor.py
RetrievalMind/data_ingestion/text_ingestor.py
RetrievalMind/embeddings_manager/__init__.py
RetrievalMind/embeddings_manager/embedding_manager.py
RetrievalMind/rag_retriver/__init__.py
RetrievalMind/rag_retriver/retriver.py
RetrievalMind/vector_store_manager/__init__.py
RetrievalMind/vector_store_manager/vector_store.py
RetrievalMind-0.1.1.dist-info/LICENSE
RetrievalMind-0.1.1.dist-info/METADATA
RetrievalMind-0.1.1.dist-info/WHEEL
RetrievalMind-0.1.1.dist-info/top_level.txt
RetrievalMind-0.1.1.dist-info/RECORD
