Metadata-Version: 2.1
Name: RetrievalMind
Version: 0.1.1
Summary: A custom Retrieval-Augmented Generation (RAG) framework for AI Agent applications.
Home-page: https://github.com/Himanshu7921/RetrievalMind
Author: Himanshu Singh
Author-email: Himanshu Singh <himanshu@example.com>
License: MIT
Classifier: Programming Language :: Python :: 3
Classifier: License :: OSI Approved :: MIT License
Classifier: Operating System :: OS Independent
Requires-Python: >=3.9
License-File: LICENSE
Requires-Dist: langchain
Requires-Dist: chromadb
Requires-Dist: sentence-transformers
Requires-Dist: PyMuPDF
